{
    "name": "Facades/HeatTemperatureLevel",
    "version": "0.0.1",
    "commands": { },
    "state": {
        "heatTemperatureLevel": {
            "readOnly": false,
            "schema": {
                "type": "number",
                "minimum": 0,
                "maximum": 200
            }
        }
    },
    "events": {
        "heatTemperatureLevel": {
            "schema": {
                "type": "number",
                "minimum": 0,
                "maximum": 200
            }
        }
    }
}